{
 "date": "2026-07-06",
 "samples": [
  "2026-07-06T08:04:29+00:00",
  "2026-07-06T15:48:07+00:00"
 ],
 "trains": {
  "887435": {
   "cancelled": false,
   "finalDelayS": 0,
   "maxDelayS": 0,
   "skippedStops": 0
  },
  "887485": {
   "cancelled": false,
   "finalDelayS": 300,
   "maxDelayS": 300,
   "skippedStops": 0
  },
  "887487": {
   "cancelled": false,
   "finalDelayS": 0,
   "maxDelayS": 0,
   "skippedStops": 0
  },
  "889382": {
   "cancelled": false,
   "finalDelayS": 0,
   "maxDelayS": 0,
   "skippedStops": 0
  },
  "889386": {
   "cancelled": false,
   "finalDelayS": 0,
   "maxDelayS": 0,
   "skippedStops": 0
  },
  "889417": {
   "cancelled": false,
   "finalDelayS": 0,
   "maxDelayS": 0,
   "skippedStops": 0
  },
  "889421": {
   "cancelled": false,
   "finalDelayS": 0,
   "maxDelayS": 0,
   "skippedStops": 0
  },
  "889433": {
   "cancelled": false,
   "finalDelayS": 0,
   "maxDelayS": 0,
   "skippedStops": 0
  },
  "889435": {
   "cancelled": false,
   "finalDelayS": 300,
   "maxDelayS": 300,
   "skippedStops": 0
  },
  "889469": {
   "cancelled": false,
   "finalDelayS": 0,
   "maxDelayS": 0,
   "skippedStops": 0
  },
  "889471": {
   "cancelled": false,
   "finalDelayS": 0,
   "maxDelayS": 0,
   "skippedStops": 0
  },
  "889483": {
   "cancelled": false,
   "finalDelayS": 0,
   "maxDelayS": 0,
   "skippedStops": 0
  },
  "889485": {
   "cancelled": false,
   "finalDelayS": 0,
   "maxDelayS": 0,
   "skippedStops": 0
  }
 }
}
